direpack/__init__.py
direpack/cross_validation/__init__.py
direpack/cross_validation/_cv_support_functions.py
direpack/dicomo/__init__.py
direpack/dicomo/_dicomo_utils.py
direpack/dicomo/dicomo.py
direpack/ipopt_temp/__init__.py
direpack/ipopt_temp/ipopt_wrapper.py
direpack/ipopt_temp/jacobian.py
direpack/plot/__init__.py
direpack/plot/ppdire_plot.py
direpack/plot/sprm_plot.py
direpack/plot/sudire_plot.py
direpack/ppdire/__init__.py
direpack/ppdire/_ppdire_utils.py
direpack/ppdire/capi.py
direpack/ppdire/ppdire.py
direpack/preprocessing/__init__.py
direpack/preprocessing/_gsspp_utils.py
direpack/preprocessing/_preproc_utilities.py
direpack/preprocessing/gsspp.py
direpack/preprocessing/robcent.py
direpack/sprm/__init__.py
direpack/sprm/_m_support_functions.py
direpack/sprm/rm.py
direpack/sprm/snipls.py
direpack/sprm/sprm.py
direpack/sudire/__init__.py
direpack/sudire/_sudire_utils.py
direpack/sudire/sudire.py
direpack/test/__init__.py
direpack/test/test_dicomo.py
direpack/test/test_ppdire.py
direpack/test/test_sprm.py
direpack/test/test_sudire.py
direpack/utils/__init__.py
direpack/utils/utils.py
direpack-1.1.2.dist-info/LICENSE
direpack-1.1.2.dist-info/METADATA
direpack-1.1.2.dist-info/WHEEL
direpack-1.1.2.dist-info/top_level.txt
direpack-1.1.2.dist-info/RECORD
