Metadata-Version: 2.1
Name: direpack
Version: 1.1.2
Summary: A Python 3 Library for State-of-the-Art Statistical Dimension Reduction Methods
Home-page: https://github.com/SvenSerneels/direpack
Author: Emmanuel Jordy Menvouta, Sven Serneels, Tim Verdonck
Author-email: svenserneels@gmail.com
License: UNKNOWN
Platform: UNKNOWN
Classifier: Programming Language :: Python :: 3
Classifier: License :: OSI Approved :: MIT License
Classifier: Operating System :: OS Independent
License-File: LICENSE
Requires-Dist: numpy (>=1.5.0)
Requires-Dist: scipy (>=0.8.0)
Requires-Dist: matplotlib (>=2.2.0)
Requires-Dist: scikit-learn (>=0.18.0)
Requires-Dist: pandas (>=0.19.0)
Requires-Dist: statsmodels (>=0.8.0)
Requires-Dist: dcor (>=0.3)
